LICENSE
README.md
pyproject.toml
anytype/__init__.py
anytype/anytype.py
anytype/api.py
anytype/icon.py
anytype/listview.py
anytype/member.py
anytype/object.py
anytype/property.py
anytype/space.py
anytype/tag.py
anytype/template.py
anytype/type.py
anytype/utils.py
anytype_client.egg-info/PKG-INFO
anytype_client.egg-info/SOURCES.txt
anytype_client.egg-info/dependency_links.txt
anytype_client.egg-info/requires.txt
anytype_client.egg-info/top_level.txt
tests/test_anytype.py