Metadata-Version: 2.4
Name: anytype-client
Version: 0.2.0
Summary:  A Python Client for Anytype.
Author-email: "Charles K. Neimog" <charlesneimog@outlook.com>
License: GPL-3.0-or-later
Project-URL: Source Code, https://github.com/charlesneimog/anytype-client
License-File: LICENSE
Requires-Dist: requests
Dynamic: license-file
